[{"__symbolic":"module","version":4,"metadata":{"SourceActionTypes":{"SOURCE_SUBMIT":"[SOURCE] source submit","SOURCE_SUBMIT_SUCCEED":"[SOURCE] source submit succeed","SOURCE_SUBMIT_FAILED":"[SOURCE] source submit failed"},"SourceSubmit":{"__symbolic":"class","members":{"__ctor__":[{"__symbolic":"constructor","parameters":[{"__symbolic":"select","expression":{"__symbolic":"reference","module":"../models","name":"UpsertSourceApiModel","line":11,"character":29},"member":"Request"}]}]}},"SourceSubmitSucceed":{"__symbolic":"class"},"SourceSubmitFailed":{"__symbolic":"class"},"Actions":{"__symbolic":"interface"}}}]